plico_interferometer/__init__.py
plico_interferometer/__version__.py
plico_interferometer/client/__init__.py
plico_interferometer/client/abstract_interferometer_client.py
plico_interferometer/client/interferometer_WCF_client.py
plico_interferometer/client/interferometer_client.py
plico_interferometer/client/simulated_interferometer_client.py
plico_interferometer/client/snapshot_entry.py
plico_interferometer/devices/WCF_interface_for_4SightFocus.py
plico_interferometer/types/__init__.py
plico_interferometer/types/interferometer_status.py
plico_interferometer/utils/__init__.py
plico_interferometer/utils/constants.py
plico_interferometer/utils/timeout.py
plico_interferometer-0.1.4.dist-info/LICENSE
plico_interferometer-0.1.4.dist-info/METADATA
plico_interferometer-0.1.4.dist-info/WHEEL
plico_interferometer-0.1.4.dist-info/top_level.txt
plico_interferometer-0.1.4.dist-info/RECORD
