Metadata-Version: 2.1
Name: plico_interferometer
Version: 0.1.4
Summary: interferometer controller with PLICO
Home-page: https://github.com/ArcetriAdaptiveOptics/plico_interferometer
Author: Lorenzo Busoni, Alfio Puglisi
Author-email: lorenzo.busoni@inaf.it
License: MIT
Keywords: plico,interferometer,laboratory,instrumentation control
Classifier: Development Status :: 4 - Beta
Classifier: Operating System :: POSIX :: Linux
Classifier: Programming Language :: Python :: 3
Classifier: Programming Language :: Python :: 2.7
License-File: LICENSE
Requires-Dist: plico>=0.18
Requires-Dist: numpy
